redisext/__init__.py
redisext/counter.py
redisext/hashmap.py
redisext/key.py
redisext/lock.py
redisext/pool.py
redisext/queue.py
redisext/serializer.py
redisext/stack.py
redisext/backend/__init__.py
redisext/backend/abc.py
redisext/backend/redis.py
redisext/backend/rmredis.py
redisext/models/__init__.py
redisext/models/abc.py
redisext/packages/__init__.py
redisext/packages/dsnparse.py
redisext-2.0.2.dist-info/LICENSE
redisext-2.0.2.dist-info/METADATA
redisext-2.0.2.dist-info/WHEEL
redisext-2.0.2.dist-info/top_level.txt
redisext-2.0.2.dist-info/RECORD
