Metadata-Version: 2.1
Name: redisext
Version: 2.0.2
Summary: Data models for Redis
Home-page: https://github.com/mylokin/redisext
Author: Andrey Gubarev
Author-email: mylokin@me.com
License: MIT
Keywords: redis,orm,models
Platform: any
Classifier: Development Status :: 4 - Beta
Classifier: Intended Audience :: Developers
Classifier: Operating System :: OS Independent
Classifier: License :: OSI Approved :: MIT License
Classifier: Programming Language :: Python
Classifier: Programming Language :: Python :: 3
Classifier: Programming Language :: Python :: 3.8
Classifier: Programming Language :: Python :: 3.9
Classifier: Programming Language :: Python :: 3.10
Classifier: Programming Language :: Python :: 3.11
Classifier: Topic :: Database
Classifier: Topic :: Database :: Database Engines/Servers
License-File: LICENSE
Requires-Dist: redis (<5,>=4)
